Workbook

Sheet 📈 Dashboard
A1: RIFT WEAR — BUSINESS DASHBOARD
A2: Auto-calculated. Do not edit manually.
A4: REVENUE
A5: Total Revenue (All Drops) | F5: ='📊 Drop Summary'!C30 -> 17346.17
A6: Site Orders Revenue | F6: ='📊 Drop Summary'!C31 -> 8785
A7: Custom Orders Revenue | F7: ='📊 Drop Summary'!C32 -> 6689
A8: Razorpay Fees Paid | F8: ='📊 Drop Summary'!C33 -> 224.83
A11: COSTS
A12: Total T-shirt Cost | F12: =SUMIF('💸 Expenses'!B:B,"T-Shirts",'💸 Expenses'!E:E) -> 5336.1
A13: Total DTF Print Cost | F13: =SUMIF('💸 Expenses'!B:B,"DTF Print",'💸 Expenses'!E:E) -> 4250
A14: Total Delivery Cost | F14: =SUMIF('💸 Expenses'!B:B,"Delivery",'💸 Expenses'!E:E) -> 0
A15: Total Marketing / Events | F15: =SUMIF('💸 Expenses'!B:B,"Marketing",'💸 Expenses'!E:E) -> 1750
A16: Total Travel | F16: =SUMIF('💸 Expenses'!B:B,"Travel",'💸 Expenses'!E:E) -> 950
A17: Total Expenses | F17: =SUM('💸 Expenses'!E:E) -> 25938.64
A19: PROFIT
A20: Gross Profit (Revenue - COGS) | F20: ='📊 Drop Summary'!C34 -> 7760.07
A21: Net Profit (After all expenses) | F21: ='📊 Drop Summary'!C35 -> 7760.07
A22: Overall Margin % | F22: ='📊 Drop Summary'!C36 -> 0.44736504
A24: ORDERS
A25: Total Orders | F25: =COUNTA('🛒 Orders'!A4:A500)-COUNTBLANK('🛒 Orders'!A4:A500) -> -443
A26: Site Orders | F26: =COUNTIF('🛒 Orders'!D4:D500,"Site") -> 15
A27: Custom Orders | F27: =COUNTIF('🛒 Orders'!D4:D500,"Custom") -> 11
A28: Dept / Bulk Orders | F28: =COUNTIF('🛒 Orders'!D4:D500,"Dept") -> 1
A29: Total Units Sold | F29: =SUM('🛒 Orders'!F4:F500) -> 29
A30: Avg Order Value | F30: =IFERROR(SUM('🛒 Orders'!H4:H500)/COUNTA('🛒 Orders'!A4:A500),0) -> 650.77778

Sheet 🛒 Orders
A1: RIFT WEAR — ORDER LOG
A2: One row per order. Order Type: Site / Custom / Dept. Payment: Razorpay / Cash / UPI / Bank
A3: Order ID | B3: Drop Name | C3: Date | D3: Order Type | E3: Customer Name | F3: Qty | G3: Product(s) | H3: Selling Price (₹) | I3: Razorpay Fee (₹) | J3: Amount Received (₹) | K3: T-shirt Cost (₹) | L3: Print Cost (₹) | M3: Delivery Cost (₹) | N3: Total COGS (₹) | O3: Profit (₹) | P3: Satisfaction
A4: RW-001 | B4: Drop 1 - Aug'24 | C4: 22-08-2024 | D4: Site | E4: Customer 1 | F4: 1 | G4: GTA Tee | H4: =VLOOKUP(G4,'👕 Products'!A:G,7,0)*F4 -> 599 | I4: =IF(D4="Site",ROUND(H4*0.0256,2),0) -> 15.33 | J4: =IF(D4="Site",H4-I4,H4) -> 583.67 | K4: =VLOOKUP(G4,'👕 Products'!A:D,4,0) -> 250 | L4: =VLOOKUP(G4,'👕 Products'!A:E,5,0) -> 150 | M4: 0 | N4: =IF(K4+L4+M4=0,"",K4+L4+M4) -> 400 | O4: =IF(H4="","",J4-N4) -> 183.67
A5: RW-002 | B5: Drop 1 - Aug'24 | C5: 23-08-2024 | D5: Site | E5: Customer 2 | F5: 1 | G5: Graffiti Tee | H5: =VLOOKUP(G5,'👕 Products'!A:G,7,0)*F5 -> 599 | I5: =IF(D5="Site",ROUND(H5*0.0256,2),0) -> 15.33 | J5: =IF(D5="Site",H5-I5,H5) -> 583.67 | K5: =VLOOKUP(G5,'👕 Products'!A:D,4,0) -> 250 | L5: =VLOOKUP(G5,'👕 Products'!A:E,5,0) -> 150 | M5: 0 | N5: =IF(K5+L5+M5=0,"",K5+L5+M5) -> 400 | O5: =IF(H5="","",J5-N5) -> 183.67
A6: RW-003 | B6: Drop 1 - Aug'24 | C6: 24-08-2024 | D6: Site | E6: Customer 3 | F6: 1 | G6: Isometric Tee | H6: =VLOOKUP(G6,'👕 Products'!A:G,7,0)*F6 -> 499 | I6: =IF(D6="Site",ROUND(H6*0.0256,2),0) -> 12.77 | J6: =IF(D6="Site",H6-I6,H6) -> 486.23 | K6: =VLOOKUP(G6,'👕 Products'!A:D,4,0) -> 200 | L6: =VLOOKUP(G6,'👕 Products'!A:E,5,0) -> 150 | M6: 0 | N6: =IF(K6+L6+M6=0,"",K6+L6+M6) -> 350 | O6: =IF(H6="","",J6-N6) -> 136.23
A7: RW-004 | B7: Drop 1 - Aug'24 | C7: 25-08-2024 | D7: Site | E7: Customer 4 | F7: 1 | G7: Classic Tee | H7: =VLOOKUP(G7,'👕 Products'!A:G,7,0)*F7 -> 499 | I7: =IF(D7="Site",ROUND(H7*0.0256,2),0) -> 12.77 | J7: =IF(D7="Site",H7-I7,H7) -> 486.23 | K7: =VLOOKUP(G7,'👕 Products'!A:D,4,0) -> 200 | L7: =VLOOKUP(G7,'👕 Products'!A:E,5,0) -> 150 | M7: 0 | N7: =IF(K7+L7+M7=0,"",K7+L7+M7) -> 350 | O7: =IF(H7="","",J7-N7) -> 136.23
A8: RW-005 | B8: Drop 1 - Aug'24 | C8: 26-08-2024 | D8: Site | E8: Customer 5 | F8: 1 | G8: GTA Tee | H8: =VLOOKUP(G8,'👕 Products'!A:G,7,0)*F8 -> 599 | I8: =IF(D8="Site",ROUND(H8*0.0256,2),0) -> 15.33 | J8: =IF(D8="Site",H8-I8,H8) -> 583.67 | K8: =VLOOKUP(G8,'👕 Products'!A:D,4,0) -> 250 | L8: =VLOOKUP(G8,'👕 Products'!A:E,5,0) -> 150 | M8: 0 | N8: =IF(K8+L8+M8=0,"",K8+L8+M8) -> 400 | O8: =IF(H8="","",J8-N8) -> 183.67
A9: RW-006 | B9: Drop 1 - Aug'24 | C9: 27-08-2024 | D9: Site | E9: Customer 6 | F9: 1 | G9: Geology Tee | H9: =VLOOKUP(G9,'👕 Products'!A:G,7,0)*F9 -> 499 | I9: =IF(D9="Site",ROUND(H9*0.0256,2),0) -> 12.77 | J9: =IF(D9="Site",H9-I9,H9) -> 486.23 | K9: =VLOOKUP(G9,'👕 Products'!A:D,4,0) -> 200 | L9: =VLOOKUP(G9,'👕 Products'!A:E,5,0) -> 150 | M9: 0 | N9: =IF(K9+L9+M9=0,"",K9+L9+M9) -> 350 | O9: =IF(H9="","",J9-N9) -> 136.23
A10: RW-007 | B10: Drop 1 - Aug'24 | C10: 28-08-2024 | D10: Site | E10: Customer 7 | F10: 1 | G10: Graffiti Tee | H10: =VLOOKUP(G10,'👕 Products'!A:G,7,0)*F10 -> 599 | I10: =IF(D10="Site",ROUND(H10*0.0256,2),0) -> 15.33 | J10: =IF(D10="Site",H10-I10,H10) -> 583.67 | K10: =VLOOKUP(G10,'👕 Products'!A:D,4,0) -> 250 | L10: =VLOOKUP(G10,'👕 Products'!A:E,5,0) -> 150 | M10: 0 | N10: =IF(K10+L10+M10=0,"",K10+L10+M10) -> 400 | O10: =IF(H10="","",J10-N10) -> 183.67
A11: RW-008 | B11: Drop 1 - Aug'24 | C11: 29-08-2024 | D11: Site | E11: Customer 8 | F11: 1 | G11: Classic Tee | H11: =VLOOKUP(G11,'👕 Products'!A:G,7,0)*F11 -> 499 | I11: =IF(D11="Site",ROUND(H11*0.0256,2),0) -> 12.77 | J11: =IF(D11="Site",H11-I11,H11) -> 486.23 | K11: =VLOOKUP(G11,'👕 Products'!A:D,4,0) -> 200 | L11: =VLOOKUP(G11,'👕 Products'!A:E,5,0) -> 150 | M11: 0 | N11: =IF(K11+L11+M11=0,"",K11+L11+M11) -> 350 | O11: =IF(H11="","",J11-N11) -> 136.23
A12: RW-009 | B12: Drop 1 - Aug'24 | C12: 30-08-2024 | D12: Site | E12: Customer 9 | F12: 1 | G12: Isometric Tee | H12: =VLOOKUP(G12,'👕 Products'!A:G,7,0)*F12 -> 499 | I12: =IF(D12="Site",ROUND(H12*0.0256,2),0) -> 12.77 | J12: =IF(D12="Site",H12-I12,H12) -> 486.23 | K12: =VLOOKUP(G12,'👕 Products'!A:D,4,0) -> 200 | L12: =VLOOKUP(G12,'👕 Products'!A:E,5,0) -> 150 | M12: 0 | N12: =IF(K12+L12+M12=0,"",K12+L12+M12) -> 350 | O12: =IF(H12="","",J12-N12) -> 136.23
A13: RW-010 | B13: Drop 1 - Aug'24 | C13: 31-08-2024 | D13: Site | E13: Customer 10 | F13: 1 | G13: GTA Tee | H13: =VLOOKUP(G13,'👕 Products'!A:G,7,0)*F13 -> 599 | I13: =IF(D13="Site",ROUND(H13*0.0256,2),0) -> 15.33 | J13: =IF(D13="Site",H13-I13,H13) -> 583.67 | K13: =VLOOKUP(G13,'👕 Products'!A:D,4,0) -> 250 | L13: =VLOOKUP(G13,'👕 Products'!A:E,5,0) -> 150 | M13: 0 | N13: =IF(K13+L13+M13=0,"",K13+L13+M13) -> 400 | O13: =IF(H13="","",J13-N13) -> 183.67
A14: RW-011 | B14: Drop 1 - Aug'24 | C14: 01-09-2024 | D14: Custom | E14: HSS Client | F14: 1 | G14: Geology Custom | H14: =VLOOKUP(G14,'👕 Products'!A:G,7,0)*F14 -> 499 | I14: =IF(D14="Site",ROUND(H14*0.0256,2),0) -> 0 | J14: =IF(D14="Site",H14-I14,H14) -> 499 | K14: =VLOOKUP(G14,'👕 Products'!A:D,4,0) -> 200 | L14: =VLOOKUP(G14,'👕 Products'!A:E,5,0) -> 200 | M14: 0 | N14: =IF(K14+L14+M14=0,"",K14+L14+M14) -> 400 | O14: =IF(H14="","",J14-N14) -> 99
A15: RW-012 | B15: Drop 1 - Aug'24 | C15: 02-09-2024 | D15: Custom | E15: Geology C1 | F15: 1 | G15: Geology Custom | H15: =VLOOKUP(G15,'👕 Products'!A:G,7,0)*F15 -> 499 | I15: =IF(D15="Site",ROUND(H15*0.0256,2),0) -> 0 | J15: =IF(D15="Site",H15-I15,H15) -> 499 | K15: =VLOOKUP(G15,'👕 Products'!A:D,4,0) -> 200 | L15: =VLOOKUP(G15,'👕 Products'!A:E,5,0) -> 200 | M15: 0 | N15: =IF(K15+L15+M15=0,"",K15+L15+M15) -> 400 | O15: =IF(H15="","",J15-N15) -> 99
... A29: RW-026 | B29: Drop 2 - Oct'24 | C29: 22-10-2024 | D29: Custom | E29: VokeAI | F29: 1 | G29: VokeAI Custom | H29: =VLOOKUP(G29,'👕 Products'!A:G,7,0)*F29 -> 499 | I29: =IF(D29="Site",ROUND(H29*0.0256,2),0) -> 0 | J29: =IF(D29="Site",H29-I29,H29) -> 499 | K29: =VLOOKUP(G29,'👕 Products'!A:D,4,0) -> 200 | L29: =VLOOKUP(G29,'👕 Products'!A:E,5,0) -> 150 | M29: 0 | N29: =IF(K29+L29+M29=0,"",K29+L29+M29) -> 350 | O29: =IF(H29="","",J29-N29) -> 149
A30: RW-027 | B30: Drop 2 - Oct'24 | C30: 23-10-2024 | D30: Dept | E30: Petro Dept | F30: 3 | G30: One Piece Tee | H30: =VLOOKUP(G30,'👕 Products'!A:G,7,0)*F30 -> 2097 | I30: =IF(D30="Site",ROUND(H30*0.0256,2),0) -> 0 | J30: =IF(D30="Site",H30-I30,H30) -> 2097 | K30: 200 | L30: 200 | M30: 0 | N30: =IF(K30+L30+M30=0,"",K30+L30+M30) -> 400 | O30: =IF(H30="","",J30-N30) -> 1697
I31: =IF(D31="Site",ROUND(H31*0.0256,2),0) -> 0 | J31: =IF(H31="","",H31-I31) | N31: =IF(K31+L31+M31=0,"",K31+L31+M31) | O31: =IF(H31="","",J31-N31)
I32: =IF(D32="Site",ROUND(H32*0.0256,2),0) -> 0 | J32: =IF(H32="","",H32-I32) | N32: =IF(K32+L32+M32=0,"",K32+L32+M32) | O32: =IF(H32="","",J32-N32)
I33: =IF(D33="Site",ROUND(H33*0.0256,2),0) -> 0 | J33: =IF(H33="","",H33-I33) | N33: =IF(K33+L33+M33=0,"",K33+L33+M33) | O33: =IF(H33="","",J33-N33)
I34: =IF(D34="Site",ROUND(H34*0.0256,2),0) -> 0 | J34: =IF(H34="","",H34-I34) | N34: =IF(K34+L34+M34=0,"",K34+L34+M34) | O34: =IF(H34="","",J34-N34)
I35: =IF(D35="Site",ROUND(H35*0.0256,2),0) -> 0 | J35: =IF(H35="","",H35-I35) | N35: =IF(K35+L35+M35=0,"",K35+L35+M35) | O35: =IF(H35="","",J35-N35)
I36: =IF(D36="Site",ROUND(H36*0.0256,2),0) -> 0 | J36: =IF(H36="","",H36-I36) | N36: =IF(K36+L36+M36=0,"",K36+L36+M36) | O36: =IF(H36="","",J36-N36)
I37: =IF(D37="Site",ROUND(H37*0.0256,2),0) -> 0 | J37: =IF(H37="","",H37-I37) | N37: =IF(K37+L37+M37=0,"",K37+L37+M37) | O37: =IF(H37="","",J37-N37)
I38: =IF(D38="Site",ROUND(H38*0.0256,2),0) -> 0 | J38: =IF(H38="","",H38-I38) | N38: =IF(K38+L38+M38=0,"",K38+L38+M38) | O38: =IF(H38="","",J38-N38)
I39: =IF(D39="Site",ROUND(H39*0.0256,2),0) -> 0 | J39: =IF(H39="","",H39-I39) | N39: =IF(K39+L39+M39=0,"",K39+L39+M39) | O39: =IF(H39="","",J39-N39)
I40: =IF(D40="Site",ROUND(H40*0.0256,2),0) -> 0 | J40: =IF(H40="","",H40-I40) | N40: =IF(K40+L40+M40=0,"",K40+L40+M40) | O40: =IF(H40="","",J40-N40)
I41: =IF(D41="Site",ROUND(H41*0.0256,2),0) -> 0 | J41: =IF(H41="","",H41-I41) | N41: =IF(K41+L41+M41=0,"",K41+L41+M41) | O41: =IF(H41="","",J41-N41)
I42: =IF(D42="Site",ROUND(H42*0.0256,2),0) -> 0 | J42: =IF(H42="","",H42-I42) | N42: =IF(K42+L42+M42=0,"",K42+L42+M42) | O42: =IF(H42="","",J42-N42)
... I60: =IF(D60="Site",ROUND(H60*0.0256,2),0) -> 0 | J60: =IF(H60="","",H60-I60) | N60: =IF(K60+L60+M60=0,"",K60+L60+M60) | O60: =IF(H60="","",J60-N60)

Sheet 💸 Expenses
A1: RIFT WEAR — EXPENSE LOG
A2: Category: T-Shirts | DTF Print | Delivery | Marketing | Travel | Domain | Miscellaneous
A3: Date | B3: Category | C3: Drop / Event | D3: Description | E3: Amount (₹) | F3: Vendor | G3: Payment Mode | H3: Notes
A4: 22-08-2024 | B4: T-Shirts | C4: Drop 1 - Aug'24 | D4: 19x T-shirts from Whiscoop | E4: 4021.5 | F4: Whiscoop | G4: Cash | H4: 211.66/T avg
A5: 22-08-2024 | B5: DTF Print | C5: Drop 1 - Aug'24 | D5: 19x DTF prints from Whiscoop | E5: 3150 | F5: Whiscoop | G5: Cash | H5: 165.79/T avg
A6: 22-08-2024 | B6: Marketing | C6: FilmFest | D6: 5 tshirts gifted at FilmFest | E6: 1750 | F6: Internal | G6: Cash | H6: Brand launch event at college
A7: 01-09-2024 | B7: Travel | C7: Bokaro Trip | D7: Travel to Bokaro for vendor meeting | E7: 950 | F7: Internal | G7: Cash | H7: Fill actual amount
A8: 01-08-2024 | B8: Domain | C8: Annual | D8: riftwear.in domain renewal | E8: 683.22 | F8: Domain Registrar | G8: UPI | H8: Annual cost
A9: 16-10-2024 | B9: T-Shirts | C9: Drop 2 - Oct'24 | D9: 7x T-shirts from OKB | E9: 1314.6 | F9: Own Knighted Blank | G9: UPI | H9: 187.8/T avg — cheaper than Whiscoop
A10: 16-10-2024 | B10: DTF Print | C10: Drop 2 - Oct'24 | D10: 7x DTF prints | E10: 1100 | F10: Local Print Vendor | G10: Cash | H10: 157.14/T avg
A24: TOTAL EXPENSES | E24: =SUM(E4:E23) -> 12969.32

Sheet 🏭 Vendors
A1: RIFT WEAR — VENDOR DIRECTORY
A2: Track all vendors — tshirt suppliers, printers, platforms
A3: Vendor Name | B3: Type | C3: City | D3: Contact | E3: Avg T-shirt Cost (₹) | F3: Avg Print Cost (₹) | G3: Min Order | H3: Payment Terms | I3: Notes
A4: Whiscoop | B4: T-shirt + Print | C4: Local | E4: 211.66 | F4: 165.79 | G4: 1 | H4: Cash | I4: 4th party — expensive. Used in Drop 1 only.
A5: Own Knighted Blank | B5: T-shirt Wholesale | C5: Online | E5: 187.8 | G5: 1 | H5: UPI | I5: Better price than Whiscoop. Used from Drop 2.
A6: Local Print Vendor | B6: DTF Print Only | C6: Local | F6: 157.14 | G6: 1 | H6: Cash | I6: Near OKB, used in Drop 2. Cheaper print.
A7: Razorpay | B7: Payment Gateway | C7: Online | G7: - | H7: 2.56% | I7: 2.56% deducted per site order automatically
A8: Domain Registrar | B8: Domain / Hosting | C8: Online | G8: - | H8: Annual | I8: riftwear.in — ₹683.22/yr

Sheet 📊 Drop Summary
A1: RIFT WEAR — DROP-WISE P&L
A2: One column per drop. Auto-calculated from Orders & Expenses sheets.
A3: Metric | B3: Drop 1 Aug–Sep '24 | C3: Drop 2 Oct '24 | D3: Drop 3 (upcoming) | E3: Drop 4 (upcoming) | F3: Drop 5 (upcoming) | G3: Drop 6 (upcoming) | H3: ALL DROPS TOTAL
A4: ── REVENUE ──
A5: Site Orders Revenue | B5: =SUMPRODUCT(('🛒 Orders'!B$4:B$500="Drop 1 - Aug'24")*('🛒 Orders'!D$4:D$500="Site")*('🛒 Orders'!H$4:H$500)) -> 5490 | C5: =SUMPRODUCT(('🛒 Orders'!B$4:B$500="Drop 2 - Oct'24")*('🛒 Orders'!D$4:D$500="Site")*('🛒 Orders'!H$4:H$500)) -> 3295 | H5: =SUM(B5:G5) -> 8785
A6: Custom Orders Revenue | B6: =SUMPRODUCT(('🛒 Orders'!B$4:B$500="Drop 1 - Aug'24")*('🛒 Orders'!D$4:D$500="Custom")*('🛒 Orders'!H$4:H$500)) -> 5491 | C6: =SUMPRODUCT(('🛒 Orders'!B$4:B$500="Drop 2 - Oct'24")*('🛒 Orders'!D$4:D$500="Custom")*('🛒 Orders'!H$4:H$500)) -> 1198 | H6: =SUM(B6:G6) -> 6689
A7: Dept / Bulk Revenue | B7: =SUMPRODUCT(('🛒 Orders'!B$4:B$500="Drop 1 - Aug'24")*('🛒 Orders'!D$4:D$500="Dept")*('🛒 Orders'!H$4:H$500)) -> 0 | C7: =SUMPRODUCT(('🛒 Orders'!B$4:B$500="Drop 2 - Oct'24")*('🛒 Orders'!D$4:D$500="Dept")*('🛒 Orders'!H$4:H$500)) -> 2097 | H7: =SUM(B7:G7) -> 2097
A8: Razorpay Fees | B8: =SUMPRODUCT(('🛒 Orders'!B$4:B$500="Drop 1 - Aug'24")*('🛒 Orders'!I$4:I$500)) -> 140.5 | C8: =SUMPRODUCT(('🛒 Orders'!B$4:B$500="Drop 2 - Oct'24")*('🛒 Orders'!I$4:I$500)) -> 84.33 | H8: =SUM(B8:G8) -> 224.83
A9: Net Revenue Received | B9: =B5+B6+B7-B8 -> 10840.5 | C9: =C5+C6+C7-C8 -> 6505.67 | H9: =SUM(B9:G9) -> 17346.17
A10: ── COSTS ──
A11: T-shirt Cost | B11: =SUMPRODUCT(('💸 Expenses'!C$4:C$500="Drop 1 - Aug'24")*('💸 Expenses'!B$4:B$500="T-Shirts")*('💸 Expenses'!E$4:E$500)) -> 4021.5 | C11: =SUMPRODUCT(('💸 Expenses'!C$4:C$500="Drop 2 - Oct'24")*('💸 Expenses'!B$4:B$500="T-Shirts")*('💸 Expenses'!E$4:E$500)) -> 1314.6 | H11: =SUM(B11:G11) -> 5336.1
A12: DTF Print Cost | B12: =SUMPRODUCT(('💸 Expenses'!C$4:C$500="Drop 1 - Aug'24")*('💸 Expenses'!B$4:B$500="DTF Print")*('💸 Expenses'!E$4:E$500)) -> 3150 | C12: =SUMPRODUCT(('💸 Expenses'!C$4:C$500="Drop 2 - Oct'24")*('💸 Expenses'!B$4:B$500="DTF Print")*('💸 Expenses'!E$4:E$500)) -> 1100 | H12: =SUM(B12:G12) -> 4250
A13: Delivery Cost | B13: =SUMPRODUCT(('💸 Expenses'!C$4:C$500="Drop 1 - Aug'24")*('💸 Expenses'!B$4:B$500="Delivery")*('💸 Expenses'!E$4:E$500)) -> 0 | C13: =SUMPRODUCT(('💸 Expenses'!C$4:C$500="Drop 2 - Oct'24")*('💸 Expenses'!B$4:B$500="Delivery")*('💸 Expenses'!E$4:E$500)) -> 0 | H13: =SUM(B13:G13) -> 0
A14: Total COGS | B14: =B11+B12+B13 -> 7171.5 | C14: =C11+C12+C13 -> 2414.6 | H14: =SUM(B14:G14) -> 9586.1
A15: ── PROFIT ──
A16: Gross Profit | B16: =B9-B14 -> 3669 | C16: =C9-C14 -> 4091.07 | H16: =SUM(B16:G16) -> 7760.07
A17: Drop-specific Expenses | B17: =SUMPRODUCT(('💸 Expenses'!C$4:C$500="Drop 1 - Aug'24")*('💸 Expenses'!B$4:B$500<>"T-Shirts")*('💸 Expenses'!B$4:B$500<>"DTF Print")*('💸 Expenses'!B$4:B$500<>"Delivery")*('💸 Expenses'!E$4:E$500)) -> 0 | C17: =SUMPRODUCT(('💸 Expenses'!C$4:C$500="Drop 2 - Oct'24")*('💸 Expenses'!B$4:B$500<>"T-Shirts")*('💸 Expenses'!B$4:B$500<>"DTF Print")*('💸 Expenses'!B$4:B$500<>"Delivery")*('💸 Expenses'!E$4:E$500)) -> 0 | D17: =0 -> 0 | E17: =0 -> 0 | F17: =0 -> 0 | G17: =0 -> 0 | H17: =SUM(B17:G17) -> 0
A18: Net Profit | B18: =B16-B17 -> 3669 | C18: =C16-C17 -> 4091.07 | H18: =SUM(B18:G18) -> 7760.07
A19: Margin % | B19: =IFERROR(B18/B9,0) -> 0.33845302 | C19: =IFERROR(C18/C9,0) -> 0.62884684 | D19: =IFERROR(D18/D9,0) -> 0 | E19: =IFERROR(E18/E9,0) -> 0 | F19: =IFERROR(F18/F9,0) -> 0 | G19: =IFERROR(G18/G9,0) -> 0 | H19: =IFERROR(H18/H9,0) -> 0.44736504
A20: ── UNITS ──
A21: Total Units Sold | B21: =SUMPRODUCT(('🛒 Orders'!B$4:B$500="Drop 1 - Aug'24")*('🛒 Orders'!F$4:F$500)) -> 19 | C21: =SUMPRODUCT(('🛒 Orders'!B$4:B$500="Drop 2 - Oct'24")*('🛒 Orders'!F$4:F$500)) -> 10 | H21: =SUM(B21:G21) -> 29
A22: Avg Selling Price | B22: =IFERROR(B9/B21,0) -> 570.55263 | C22: =IFERROR(C9/C21,0) -> 650.567 | D22: =IFERROR(D9/D21,0) -> 0 | E22: =IFERROR(E9/E21,0) -> 0 | F22: =IFERROR(F9/F21,0) -> 0 | G22: =IFERROR(G9/G21,0) -> 0 | H22: =IFERROR(H9/H21,0) -> 598.14379
A23: Cost per Unit | B23: =IFERROR(B14/B21,0) -> 377.44737 | C23: =IFERROR(C14/C21,0) -> 241.46 | D23: =IFERROR(D14/D21,0) -> 0 | E23: =IFERROR(E14/E21,0) -> 0 | F23: =IFERROR(F14/F21,0) -> 0 | G23: =IFERROR(G14/G21,0) -> 0 | H23: =IFERROR(H14/H21,0) -> 330.55517
A24: Profit per Unit | B24: =IFERROR(B18/B21,0) -> 193.10526 | C24: =IFERROR(C18/C21,0) -> 409.107 | D24: =IFERROR(D18/D21,0) -> 0 | E24: =IFERROR(E18/E21,0) -> 0 | F24: =IFERROR(F18/F21,0) -> 0 | G24: =IFERROR(G18/G21,0) -> 0 | H24: =IFERROR(H18/H21,0) -> 267.58862
A25: ── OTHER ──
A26: Customer Satisfaction | B26: 50% | C26: 80%
A27: Delivery Date | B27: 24-09-2024 | C27: 15-11-2024
A30: Total Revenue All | C30: =SUM(B9:G9) -> 17346.17
A31: Site Revenue Total | C31: =SUM(B5:G5) -> 8785
A32: Custom Revenue Total | C32: =SUM(B6:G6) -> 6689
A33: Razorpay Total | C33: =SUM(B8:G8) -> 224.83
A34: Gross Profit Total | C34: =SUM(B16:G16) -> 7760.07
A35: Net Profit Total | C35: =SUM(B18:G18) -> 7760.07
A36: Overall Margin | C36: =IFERROR(C35/C30,0) -> 0.44736504

Sheet 👕 Products
A1: RIFT WEAR — PRODUCT CATALOG & COGS
A2: Update costs here per drop. COGS = T-shirt cost + Print cost per unit
A3: Product Name | B3: Drop | C3: Design | D3: T-shirt Cost (₹) | E3: Print Cost (₹) | F3: COGS per Unit (₹) | G3: Selling Price (₹) | H3: Margin (₹) | I3: Margin % | J3: Vendor Used
A4: GTA Tee | B4: Drop 1 | C4: GTA Design | D4: 250 | E4: 150 | F4: =D4+E4 -> 400 | G4: 599 | H4: =IF(G4="","",G4-F4) -> 199 | I4: =IF(G4="","",IFERROR(H4/G4,0)) -> 0.33222037 | J4: Whiscoop
A5: Graffiti Tee | B5: Drop 1 | C5: Graffiti Design | D5: 250 | E5: 150 | F5: =D5+E5 -> 400 | G5: 599 | H5: =IF(G5="","",G5-F5) -> 199 | I5: =IF(G5="","",IFERROR(H5/G5,0)) -> 0.33222037 | J5: Whiscoop
A6: Isometric Tee | B6: Drop 1 | C6: Isometric Design | D6: 200 | E6: 150 | F6: =D6+E6 -> 350 | G6: 499 | H6: =IF(G6="","",G6-F6) -> 149 | I6: =IF(G6="","",IFERROR(H6/G6,0)) -> 0.29859719 | J6: Whiscoop
A7: Classic Tee | B7: Drop 1 | C7: Classic Design | D7: 200 | E7: 150 | F7: =D7+E7 -> 350 | G7: 499 | H7: =IF(G7="","",G7-F7) -> 149 | I7: =IF(G7="","",IFERROR(H7/G7,0)) -> 0.29859719 | J7: Whiscoop
A8: Geology Tee | B8: Drop 1 | C8: Geology Design | D8: 200 | E8: 150 | F8: =D8+E8 -> 350 | G8: 499 | H8: =IF(G8="","",G8-F8) -> 149 | I8: =IF(G8="","",IFERROR(H8/G8,0)) -> 0.29859719 | J8: Whiscoop
A9: Geology Custom | B9: Drop 1 | C9: Custom | D9: 200 | E9: 200 | F9: =D9+E9 -> 400 | G9: 499 | H9: =IF(G9="","",G9-F9) -> 99 | I9: =IF(G9="","",IFERROR(H9/G9,0)) -> 0.19839679 | J9: Whiscoop
A10: Anime Custom | B10: Drop 1 | C10: Custom Anime | D10: 300 | E10: 200 | F10: =D10+E10 -> 500 | G10: 699 | H10: =IF(G10="","",G10-F10) -> 199 | I10: =IF(G10="","",IFERROR(H10/G10,0)) -> 0.28469242 | J10: Whiscoop
A11: HSS Custom | B11: Drop 1 | C11: Custom HSS | D11: 200 | E11: 150 | F11: =D11+E11 -> 350 | G11: =E11+F11 -> 500 | H11: =IF(G11="","",G11-F11) -> 150 | I11: =IF(G11="","",IFERROR(H11/G11,0)) -> 0.3 | J11: Whiscoop
A12: One Piece Tee | B12: Drop 2 | C12: One Piece Design | D12: 200 | E12: 200 | F12: =D12+E12 -> 400 | G12: 699 | H12: =IF(G12="","",G12-F12) -> 299 | I12: =IF(G12="","",IFERROR(H12/G12,0)) -> 0.42775393 | J12: OKB + Local Print
A13: Premium Tee | B13: Drop 2 | C13: Premium Design | D13: 200 | E13: 200 | F13: =D13+E13 -> 400 | G13: 599 | H13: =IF(G13="","",G13-F13) -> 199 | I13: =IF(G13="","",IFERROR(H13/G13,0)) -> 0.33222037 | J13: OKB + Local Print
A14: Zoro Custom | B14: Drop 2 | C14: Custom Zoro | D14: 200 | E14: 200 | F14: =D14+E14 -> 400 | G14: 699 | H14: =IF(G14="","",G14-F14) -> 299 | I14: =IF(G14="","",IFERROR(H14/G14,0)) -> 0.42775393 | J14: OKB + Local Print
A15: VokeAI Custom | B15: Drop 2 | C15: Custom VokeAI | D15: 200 | E15: 150 | F15: =D15+E15 -> 350 | G15: 499 | H15: =IF(G15="","",G15-F15) -> 149 | I15: =IF(G15="","",IFERROR(H15/G15,0)) -> 0.29859719 | J15: OKB + Local Print
